password_generator.py
random_password_generator-2.1.2.dist-info/LICENSE
random_password_generator-2.1.2.dist-info/WHEEL
random_password_generator-2.1.2.dist-info/METADATA
random_password_generator-2.1.2.dist-info/RECORD
