Metadata-Version: 2.1
Name: random-password-generator
Version: 2.1.2
Summary: Simple and custom random password generator for python
Home-page: https://github.com/suryasr007/random-password-generator
License: MIT
Keywords: random,password,generator,different,lengths
Author: Surya Teja
Author-email: 94suryateja@gmail.com
Requires-Python: >=3.7,<4.0
Classifier: Development Status :: 5 - Production/Stable
Classifier: Intended Audience :: Information Technology
Classifier: License :: OSI Approved :: MIT License
Classifier: Natural Language :: English
Classifier: Operating System :: POSIX
Classifier: Programming Language :: Python :: 3
Classifier: Programming Language :: Python :: 3.5
Classifier: Programming Language :: Python :: 3.6
Classifier: Programming Language :: Python :: 3.7
Classifier: Programming Language :: Python :: 3.8
Classifier: Programming Language :: Python :: 3.9
Classifier: Topic :: Utilities
Requires-Dist: Flask-RESTful
Requires-Dist: marshmallow
Requires-Dist: webargs
